ai_rules/__init__.py
ai_rules/cli.py
ai_rules/config.py
ai_rules/py.typed
ai_rules/scripts.py
ai_rules/core/__init__.py
ai_rules/core/config.py
ai_rules/core/decorators.py
ai_rules/core/http_client.py
ai_rules/core/models.py
ai_rules/core/plugin.py
ai_rules/core/template.py
ai_rules/plugins/__init__.py
ai_rules/plugins/duckduckgo_search.py
ai_rules/plugins/image_search.py
ai_rules/plugins/local_search.py
ai_rules/plugins/news_search.py
ai_rules/plugins/translate.py
ai_rules/plugins/web_scraper.py
ai_rules/processors/__init__.py
ai_rules/processors/llm_optimize.py
ai_rules/templates/base_template.yaml
ai_rules/templates/cline_template.yaml
ai_rules/templates/cursor_template.yaml
ai_rules/templates/windsurf_template.yaml
ai_rules/templates/markdown_templates/base.md
ai_rules-0.3.0.dist-info/METADATA
ai_rules-0.3.0.dist-info/WHEEL
ai_rules-0.3.0.dist-info/entry_points.txt
ai_rules-0.3.0.dist-info/licenses/LICENSE
ai_rules-0.3.0.dist-info/RECORD
