Metadata-Version: 2.4
Name: ai-rules
Version: 0.3.0
Summary: A powerful CLI toolkit for extending and enhancing AI capabilities through customizable rules and commands.
Project-URL: Homepage, https://github.com/loonghao/ai-rules-cli
Project-URL: Documentation, https://github.com/loonghao/ai-rules-cli#readme
Project-URL: Repository, https://github.com/loonghao/ai-rules-cli.git
Project-URL: Issues, https://github.com/loonghao/ai-rules-cli/issues
Author-email: loonghao <hal.long@outlook.com>
License: MIT License
License-File: LICENSE
Keywords: ai,ai-assistant,cli,prompt-engineering,rules,uv
Classifier: Development Status :: 3 - Alpha
Classifier: Intended Audience :: Developers
Classifier: License :: OSI Approved :: MIT License
Classifier: Programming Language :: Python :: 3
Classifier: Programming Language :: Python :: 3.9
Classifier: Programming Language :: Python :: 3.10
Classifier: Programming Language :: Python :: 3.11
Classifier: Programming Language :: Python :: 3.12
Classifier: Programming Language :: Python :: 3.13
Requires-Python: >=3.9
Requires-Dist: aiofiles>=24.1.0
Requires-Dist: aiohttp>=3.9.0
Requires-Dist: beautifulsoup4>=4.12.0
Requires-Dist: brotli>=1.1.0
Requires-Dist: click>=8.0.0
Requires-Dist: deep-translator>=1.11.4
Requires-Dist: googletrans>=4.0.0
Requires-Dist: html2text>=2024.2.26
Requires-Dist: httpx>=0.26.0
Requires-Dist: importlib-metadata>=8.5.0
Requires-Dist: jinja2>=3.1.5
Requires-Dist: markdown>=3.7
Requires-Dist: playwright>=1.40.0
Requires-Dist: pydantic>=2.5.3
Requires-Dist: pyyaml>=6.0.0
Requires-Dist: requests>=2.25.0
Requires-Dist: tomli-w>=1.0.0
Requires-Dist: tomli>=2.0.1
Requires-Dist: uv>=0.5.18
Requires-Dist: whoosh>=2.7.4
Provides-Extra: dev
Requires-Dist: black>=23.0.0; extra == 'dev'
Requires-Dist: isort>=5.0.0; extra == 'dev'
Requires-Dist: nox>=2023.0.0; extra == 'dev'
Requires-Dist: pyright>=1.1.0; extra == 'dev'
Requires-Dist: python-dotenv>=1.0.0; extra == 'dev'
Requires-Dist: ruff>=0.1.14; extra == 'dev'
Provides-Extra: test
Requires-Dist: pytest-asyncio>=0.25.0; extra == 'test'
Requires-Dist: pytest-cov>=6.0.0; extra == 'test'
Requires-Dist: pytest-mock>=3.14.0; extra == 'test'
Requires-Dist: pytest>=8.0.0; extra == 'test'
